Workbook
Name aporte: Invest!$E$17
Name patrimonio: Invest!$E$20
Name qtd_anos: Invest!$E$18
Name rendimento_carteira: Invest!$E$13
Name salario: Invest!$E$12
Name sugestao_investimento: Invest!$E$14
Name taxa_mensal: Invest!$E$19

Sheet Invest
B11: INFORMAÇÕES
B12: Salário | E12: 1700
B13: Rendimento Carteira | E13: 0.0103
B14: Sugestão de Investimento (30%) | E14: =E12*30% -> 510
B16: INVESTIMENTO MENSAL
B17: Qaunto Investir por Mês? | E17: 200
B18: Por Quantos Anos? | E18: 5
B19: Taxa de Rendimento Mensal? | E19: 0.0104
B20: Patrimônio Acumulado? | E20: =FV(taxa_mensal,qtd_anos*12,aporte*-1) -> 16545.653
B21: Dividendo Mensais? | E21: =patrimonio*rendimento_carteira -> 170.42023
B23: TEMPO (ANOS) | E23: DIVIDENDO
A24: 2 | B24: Quantos em 2 anos? | D24: =FV(taxa_mensal,A24*12,aporte*-1) -> 5420.3565 | E24: =D24*rendimento_carteira -> 55.829672
A25: 5 | B25: Quantos em 5 anos? | D25: =FV(taxa_mensal,A25*12,aporte*-1) -> 16545.653 | E25: =D25*rendimento_carteira -> 170.42023
A26: 10 | B26: Quantos em 10 anos? | D26: =FV(taxa_mensal,A26*12,aporte*-1) -> 47326.755 | E26: =D26*rendimento_carteira -> 487.46558
A27: 20 | B27: Quantos em 20 anos? | D27: =FV(taxa_mensal,A27*12,aporte*-1) -> 211124.24 | E27: =D27*rendimento_carteira -> 2174.5797
A28: 30 | B28: Quantos em 30 anos? | D28: =FV(taxa_mensal,A28*12,aporte*-1) -> 778025.92 | E28: =D28*rendimento_carteira -> 8013.667
B31: Perfil | D31: Agressivo
B32: Valor a ser investido por mês | D32: =aporte -> 200
B34: Tipo de FII | C34: Percentual sugerido | D34: Valores
B35: PAPEL | C35: =VLOOKUP($D$31&"-"&B35,Inf.!$A:$D,4,FALSE) -> 0.5 | D35: =C35*$D$32 -> 100
B36: TIJOLO | C36: =VLOOKUP($D$31&"-"&B36,Inf.!$A:$D,4,FALSE) -> 0.1 | D36: =C36*$D$32 -> 20
B37: HIBRIDO | C37: =VLOOKUP($D$31&"-"&B37,Inf.!$A:$D,4,FALSE) -> 0.05 | D37: =C37*$D$32 -> 10
B38: FOFs | C38: =VLOOKUP($D$31&"-"&B38,Inf.!$A:$D,4,FALSE) -> 0.05 | D38: =C38*$D$32 -> 10
B39: DESENVOLVIMENTO | C39: =VLOOKUP($D$31&"-"&B39,Inf.!$A:$D,4,FALSE) -> 0.2 | D39: =C39*$D$32 -> 40
B40: HOTELARIAS | C40: =VLOOKUP($D$31&"-"&B40,Inf.!$A:$D,4,FALSE) -> 0.1 | D40: =C40*$D$32 -> 20
D41: =SUM(D35:D40) -> 200

Sheet Inf.
A2: Chave | B2: Perfil | C2: Tipo de FII | D2: %
A3: =B3&"-"&C3 -> Conservador-PAPEL | B3: Conservador | C3: PAPEL | D3: 0.3
A4: =B4&"-"&C4 -> Conservador-TIJOLO | B4: Conservador | C4: TIJOLO | D4: 0.5
A5: =B5&"-"&C5 -> Conservador-HIBRIDO | B5: Conservador | C5: HIBRIDO | D5: 0.1
A6: =B6&"-"&C6 -> Conservador-FOFs | B6: Conservador | C6: FOFs | D6: 0.1
A7: =B7&"-"&C7 -> Conservador-DESENVOLVIMENTO | B7: Conservador | C7: DESENVOLVIMENTO | D7: 0
A8: =B8&"-"&C8 -> Conservador-HOTELARIAS | B8: Conservador | C8: HOTELARIAS | D8: 0
A9: =B9&"-"&C9 -> Moderado-PAPEL | B9: Moderado | C9: PAPEL | D9: 0.32
A10: =B10&"-"&C10 -> Moderado-TIJOLO | B10: Moderado | C10: TIJOLO | D10: 0.35
A11: =B11&"-"&C11 -> Moderado-HIBRIDO | B11: Moderado | C11: HIBRIDO | D11: 0.08
A12: =B12&"-"&C12 -> Moderado-FOFs | B12: Moderado | C12: FOFs | D12: 0.05
A13: =B13&"-"&C13 -> Moderado-DESENVOLVIMENTO | B13: Moderado | C13: DESENVOLVIMENTO | D13: 0.1
A14: =B14&"-"&C14 -> Moderado-HOTELARIAS | B14: Moderado | C14: HOTELARIAS | D14: 0.1
... A20: =B20&"-"&C20 -> Agressivo-HOTELARIAS | B20: Agressivo | C20: HOTELARIAS | D20: 0.1
